rid/__about__.py
rid/__init__.py
rid/__main__.py
rid/constants.py
rid/main.py
rid/common/__init__.py
rid/common/mol.py
rid/common/mol_dpdata.py
rid/common/gromacs/__init__.py
rid/common/gromacs/command.py
rid/common/gromacs/gmx_constant.py
rid/common/gromacs/mdp.py
rid/common/gromacs/trjconv.py
rid/common/lammps/__init__.py
rid/common/lammps/command.py
rid/common/lammps/lmp_constant.py
rid/common/plumed/__init__.py
rid/common/plumed/check_plumed.py
rid/common/plumed/make_plumed.py
rid/common/plumed/plumed_constant.py
rid/common/sampler/__init__.py
rid/common/sampler/command.py
rid/common/tensorflow/__init__.py
rid/common/tensorflow/graph.py
rid/entrypoint/__init__.py
rid/entrypoint/cli.py
rid/entrypoint/download.py
rid/entrypoint/explore.py
rid/entrypoint/info.py
rid/entrypoint/label.py
rid/entrypoint/main.py
rid/entrypoint/redim.py
rid/entrypoint/relabel.py
rid/entrypoint/reredim.py
rid/entrypoint/resubmit.py
rid/entrypoint/server.py
rid/entrypoint/submit.py
rid/entrypoint/train.py
rid/flow/__init__.py
rid/flow/loop.py
rid/mcmc/__init__.py
rid/mcmc/walker.py
rid/nn/__init__.py
rid/nn/freeze.py
rid/nn/model.py
rid/nn/train_net.py
rid/op/__init__.py
rid/op/adjust_trust_level.py
rid/op/label_stats.py
rid/op/mcmc_plot.py
rid/op/mcmc_run.py
rid/op/prep_data.py
rid/op/prep_exploration.py
rid/op/prep_label.py
rid/op/prep_rid.py
rid/op/prep_select.py
rid/op/recorder.py
rid/op/run_exploration.py
rid/op/run_label.py
rid/op/run_model_devi.py
rid/op/run_select.py
rid/op/run_train.py
rid/select/__init__.py
rid/select/cluster.py
rid/select/conf_select.py
rid/select/model_devi.py
rid/superop/__init__.py
rid/superop/blocks.py
rid/superop/data.py
rid/superop/exploration.py
rid/superop/label.py
rid/superop/mcmc.py
rid/superop/selector.py
rid/task/__init__.py
rid/task/builder.py
rid/task/task.py
rid/template/machine_bohrium.json
rid/template/machine_bohrium_k8s.json
rid/template/machine_bohrium_k8s_mcmc.json
rid/template/machine_local_k8s.json
rid/template/machine_slurm_k8s.json
rid_kit-0.6.4.dist-info/LICENSE
rid_kit-0.6.4.dist-info/METADATA
rid_kit-0.6.4.dist-info/WHEEL
rid_kit-0.6.4.dist-info/entry_points.txt
rid_kit-0.6.4.dist-info/top_level.txt
rid_kit-0.6.4.dist-info/RECORD
