Metadata-Version: 2.1
Name: rid-kit
Version: 0.6.4
Summary: RiD package for enhanced sampling
Home-page: https://github.com/deepmodeling/rid-kit
Author: Yanze Wang, Jiahao Fan
Author-email: yanze039@mit.edu,jiahaofan@pku.edu.cn
License: UNKNOWN
Keywords: enhanced sampling reinforced dynamics RiD
Platform: UNKNOWN
Classifier: Programming Language :: Python :: 3.6
Classifier: License :: OSI Approved :: GNU Lesser General Public License v3 (LGPLv3)
Requires-Python: >=3.6
License-File: LICENSE
Requires-Dist: protobuf ==3.20.1
Requires-Dist: scikit-learn
Requires-Dist: pydflow
Requires-Dist: tensorflow ==2.6.2
Requires-Dist: typeguard ==2.10.0
Requires-Dist: pandas ==1.4.4
Requires-Dist: scipy ==1.10.1
Requires-Dist: matplotlib ==3.6.3
Requires-Dist: dargs ==0.3.5
Requires-Dist: dpdispatcher ==0.6.0
Requires-Dist: google
Requires-Dist: mdtraj
Requires-Dist: dpdata
Requires-Dist: parmed
Requires-Dist: dpdispatcher
Requires-Dist: lbg
Requires-Dist: matplotlib
